fastProxy/__init__.py
fastProxy/fastProxy.py
fastProxy/logger.py
fastProxy-1.0.0.dist-info/LICENSE
fastProxy-1.0.0.dist-info/METADATA
fastProxy-1.0.0.dist-info/WHEEL
fastProxy-1.0.0.dist-info/top_level.txt
fastProxy-1.0.0.dist-info/RECORD
